<default>
  <fnames>
    <soil_decomp>
      <sys>'f_sys_npools'</sys>
      <solver>'plsoda'</solver>
      <solver_func>'f_solver_func_mimics'</solver_func>
      <input>'f_input_mimics'</input>
      <decomp>
        <d1>'f_decomp_rmm_wieder'</d1>
        <d2>'f_decomp_rmm_wieder'</d2>
        <d3>'f_decomp_lin'</d3>
        <d4>'f_decomp_lin'</d4>
        <d5>'f_zero'</d5>
        <d6>'f_decomp_rmm_wieder'</d6>
        <d7>'f_decomp_rmm_wieder'</d7>
      </decomp>
      <desorp>
        <ds5>'f_decomp_lin'</ds5>
      </desorp>
      <tcor>
        <t1>'f_tcor_wieder'</t1>
      </tcor>
    </soil_decomp>
  </fnames>
  <pars>
    <soil_decomp>
      <n_pools>7</n_pools>
      <cstate0>
        <cstate01>0.72057305</cstate01>
        <cstate02>3.66903907</cstate02>
        <cstate03>0.08525724</cstate03>
        <cstate04>0.23363596</cstate04>
        <cstate05>17.54120654</cstate05>
        <cstate06>2.27314631</cstate06>
        <cstate07>3.21888538</cstate07>
      </cstate0>
      <cue>
        <cue1>0.5</cue1>
        <cue2>0.25</cue2>
        <cue3>0</cue3>
        <cue4>0</cue4>
        <cue5>0</cue5>
        <cue6>0</cue6>
        <cue7>0.5</cue7>
      </cue>
      <cue2>
        <cue1>0.7</cue1>
        <cue2>0.35</cue2>
        <cue3>0</cue3>
        <cue4>0</cue4>
        <cue5>0</cue5>
        <cue6>0</cue6>
        <cue7>0.7</cue7>
      </cue2>
      <vmax>
        <vmax1>10</vmax1>
        <vmax2>2</vmax2>
        <vmax3>NA</vmax3>
        <vmax4>NA</vmax4>
        <vmax5>NA</vmax5>
        <vmax6>NA</vmax6>
        <vmax7>10</vmax7>
      </vmax>
      <vmax2>
        <vmax1>3</vmax1>
        <vmax2>3</vmax2>
        <vmax3>NA</vmax3>
        <vmax4>NA</vmax4>
        <vmax5>NA</vmax5>
        <vmax6>NA</vmax6>
        <vmax7>2</vmax7>
      </vmax2>
      <km>
        <km1>8</km1>
        <km2>2</km2>
        <km3>NA</km3>
        <km4>NA</km4>
        <km5>NA</km5>
        <km6>NA</km6>
        <km7>4</km7>
      </km>
      <km2>
        <km1>2</km1>
        <km2>4</km2>
        <km3>NA</km3>
        <km4>NA</km4>
        <km5>NA</km5>
        <km6>NA</km6>
        <km7>6</km7>
      </km2>
      <k>
        <k1>NA</k1>
        <k2>NA</k2>
        <k3>NA</k3>
        <k4>NA</k4>
        <k5>NA</k5>
        <k6>NA</k6>
        <k7>NA</k7>
      </k>
      <mimics>
        <fmet_p1>0.5</fmet_p1>
        <fmet_p2>0.85</fmet_p2>
        <fmet_p3>0.013</fmet_p3>
        <tau_mod1_p1>100</tau_mod1_p1>
        <tau_mod1_p2>0.6</tau_mod1_p2>
        <tau_mod1_p3>1.3</tau_mod1_p3>
        <tau_r_p1>0.00052</tau_r_p1>
        <tau_r_p2>0.3</tau_r_p2>
        <tau_mod2>2.0</tau_mod2>
        <tau_k_p1>0.00024</tau_k_p1>
        <tau_k_p2>0.1</tau_k_p2>
        <desorb_p1>0.00002</desorb_p1>
        <desorb_p2>-4.5</desorb_p2>
        <fSOMp_r_p1>0.15</fSOMp_r_p1>
        <fSOMp_r_p2>1.3</fSOMp_r_p2>
        <fSOMc_r_p1>0.1</fSOMc_r_p1>
        <fSOMc_r_p2>-3.0</fSOMc_r_p2>
        <fSOMc_r_p3>1.0</fSOMc_r_p3>
        <fSOMp_k_p1>0.1</fSOMp_k_p1>
        <fSOMp_k_p2>0.8</fSOMp_k_p2>
        <fSOMc_k_p1>0.3</fSOMc_k_p1>
        <fSOMc_k_p2>-3.0</fSOMc_k_p2>
        <fSOMc_k_p3>1.0</fSOMc_k_p3>
        <V_slope>0.063</V_slope>
        <V_int>5.47</V_int>
        <aV>0.000000125</aV>
        <pscalar_p1>3.0</pscalar_p1>
        <pscalar_p2>-2.0</pscalar_p2>
        <ko_r>6.0</ko_r>
        <ko_k>6.0</ko_k>
        <K_slope>0.02</K_slope>
        <K_int>3.19</K_int>
        <aK>0.15625</aK>
        <fi_LITm>0.005</fi_LITm>
        <fi_LITm>0.005</fi_LITm>
      </mimics>
    </soil_decomp>
  </pars>
  <env>
    <soil_decomp>
      <temp>20.0</temp>
      <clay>0.4</clay>
      <lignin>16.6</lignin>
      <N>1.37</N>
      <anpp>500</anpp>
      <depth>20.0</depth>
    </soil_decomp>
  </env>
</default>