<default>
  <fnames>
    <soil_decomp>
      <sys>'f_sys_npools'</sys>
      <solver>'plsoda'</solver>
      <solver_func>'f_solver_func_elmv2ctc'</solver_func>
      <input>'f_input'</input>
      <steadystate>'f_steadystate_npools'</steadystate>
      <solver_steadystate>'pstode'</solver_steadystate>
      <decomp>
        <d1>'f_decomp_lin'</d1>
        <d2>'f_decomp_lin'</d2>
        <d3>'f_decomp_lin'</d3>
        <d4>'f_decomp_lin'</d4>
        <d5>'f_decomp_lin'</d5>
        <d6>'f_decomp_lin'</d6>
        <d7>'f_decomp_lin'</d7>
      </decomp>
    </soil_decomp>
  </fnames>
  <pars>
    <soil_decomp>
      <n_pools>7</n_pools>
      <input_coefs>
        <input_coef1>0.1</input_coef1>
        <input_coef2>0.2</input_coef2>
        <input_coef3>0.5</input_coef3>
        <input_coef4>0.3</input_coef4>
        <input_coef5>0.5</input_coef5>
        <input_coef6>0.5</input_coef6>
        <input_coef7>NA</input_coef7>
      </input_coefs>
      <cstate0>
        <cstate01>0.1</cstate01>
        <cstate02>0.1</cstate02>
        <cstate03>0.1</cstate03>
        <cstate04>0.1</cstate04>
        <cstate05>0.1</cstate05>
        <cstate06>0.1</cstate06>
        <cstate07>0.1</cstate07>
      </cstate0>
      <cue>
        <cue1>1</cue1>
        <cue2>0.61</cue2>
        <cue3>0.45</cue3>
        <cue4>0.71</cue4>
        <cue5>0.72</cue5>
        <cue6>0.54</cue6>
        <cue7>1</cue7>
      </cue>
      <k>
        <k1>0.001</k1>
        <k2>0.7</k2>
        <k3>0.07</k3>
        <k4>0.014</k4>
        <k5>0.07</k5>
        <k6>0.014</k6>
        <k7>0.0005</k7>
      </k>
    </soil_decomp>
  </pars>
  <env>
    <soil_decomp>
      <litter>1.0</litter>
    </soil_decomp>
  </env>
</default>