<default>
  <fnames>
    <soil_decomp>
      <sys>'f_sys_npools'</sys>
      <decomp>
        <d1>'f_decomp_MM_microbe'</d1>
        <d2>'f_decomp_lin'</d2>
        <d3>'f_decomp_MM_microbe'</d3>
      </decomp>
      <transfer>
        <t1_to_2>'f_transfer_cue'</t1_to_2>
        <t2_to_3>'f_transfer_cue'</t2_to_3>
        <t3_to_2>'f_transfer_cue'</t3_to_2>
      </transfer>
    </soil_decomp>
  </fnames>
  <pars>
    <soil_decomp>
      <cstate0>
        <c1>0.6</c1>
        <c2>0.1</c2>
        <c3>0.1</c3>
      </cstate0>
      <ks>1.8e-05</ks>
      <kb>0.007</kb>
      <Km>900</Km>
      <r>0.6</r>
      <Af>1</Af>
      <silt>0.2</silt>
      <clay>0.2</clay>
      <cuec1>0.47</cuec1>
      <h>0.566</h>
      <cuec3>0.47</cuec3>
      <vmax1>0.2346</vmax1>
      <vmax3>0.0777</vmax3>
      <km1>101</km1>
      <km3>250</km3>
      <k23>0.00672</k23>
      <mbcmax>2</mbcmax>
      <beta>1.5</beta>
      <maommax>26.725</maommax>
      <cue>
        <cue1>0.47</cue1>
        <cue2>0.566</cue2>
        <cue3>0.47</cue3>
      </cue>
      <vmax>
        <vmax1>0.2346</vmax1>
        <vmax2>0.2346</vmax2>
        <vmax3>0.0777</vmax3>
      </vmax>
      <km>
        <km1>101</km1>
        <km2>101</km2>
        <km3>250</km3>
      </km>
      <k>
        <k1>0.007</k1>
        <k2>0.00672</k2>
        <k3>0.006</k3>
      </k>
      <poolmax>
        <pmax1>2</pmax1>
        <pmax2>2</pmax2>
        <pmax3>26.725</pmax3>
      </poolmax>
    </soil_decomp>
  </pars>
  <env>
    <soil_decomp>
      <litter>3.2</litter>
      <temp>10</temp>
      <swc>0.3</swc>
    </soil_decomp>
  </env>
</default>